README.md
setup.py
test/test_invoice.py
transactionpro/__init__.py
transactionpro/import_type.py
transactionpro/keyword_header_map.py
transactionpro.egg-info/PKG-INFO
transactionpro.egg-info/SOURCES.txt
transactionpro.egg-info/dependency_links.txt
transactionpro.egg-info/requires.txt
transactionpro.egg-info/top_level.txt
transactionpro/import_types/__init__.py
transactionpro/import_types/invoice.py
transactionpro/import_types/receive_payment.py