Metadata-Version: 1.0
Name: transactionpro
Version: 0.0.4
Summary: Generate csv files for TransactionPro 6.0
Home-page: https://github.com/wontonst/transactionpro-py
Author: Roy Zheng
Author-email: roycraft3@gmail.com
License: MIT
Keywords: transactionpro transaction pro csv import
Platform: UNKNOWN
